MANIFEST.in
README.rst
requirements.txt
setup.py
stestdata/__init__.py
stestdata/testdata.py
stestdata/version.py
stestdata.egg-info/PKG-INFO
stestdata.egg-info/SOURCES.txt
stestdata.egg-info/dependency_links.txt
stestdata.egg-info/requires.txt
stestdata.egg-info/top_level.txt
stestdata/data/landsat8/small_full_data_cloudy/l8_B1.tif
stestdata/data/landsat8/small_full_data_cloudy/l8_B10.tif
stestdata/data/landsat8/small_full_data_cloudy/l8_B11.tif
stestdata/data/landsat8/small_full_data_cloudy/l8_B2.tif
stestdata/data/landsat8/small_full_data_cloudy/l8_B3.tif
stestdata/data/landsat8/small_full_data_cloudy/l8_B4.tif
stestdata/data/landsat8/small_full_data_cloudy/l8_B5.tif
stestdata/data/landsat8/small_full_data_cloudy/l8_B6.tif
stestdata/data/landsat8/small_full_data_cloudy/l8_B7.tif
stestdata/data/landsat8/small_full_data_cloudy/l8_B8.tif
stestdata/data/landsat8/small_full_data_cloudy/l8_B9.tif
stestdata/data/landsat8/small_full_data_cloudy/l8_BQA.tif
stestdata/data/sentinel2/small_full_data_nocloud/preview.jp2
stestdata/data/sentinel2/small_full_data_nocloud/s2_B01.jp2
stestdata/data/sentinel2/small_full_data_nocloud/s2_B02.jp2
stestdata/data/sentinel2/small_full_data_nocloud/s2_B03.jp2
stestdata/data/sentinel2/small_full_data_nocloud/s2_B04.jp2
stestdata/data/sentinel2/small_full_data_nocloud/s2_B05.jp2
stestdata/data/sentinel2/small_full_data_nocloud/s2_B06.jp2
stestdata/data/sentinel2/small_full_data_nocloud/s2_B07.jp2
stestdata/data/sentinel2/small_full_data_nocloud/s2_B08.jp2
stestdata/data/sentinel2/small_full_data_nocloud/s2_B09.jp2
stestdata/data/sentinel2/small_full_data_nocloud/s2_B10.jp2
stestdata/data/sentinel2/small_full_data_nocloud/s2_B11.jp2
stestdata/data/sentinel2/small_full_data_nocloud/s2_B12.jp2
stestdata/data/sentinel2/small_full_data_nocloud/s2_B8A.jp2