Metadata-Version: 1.1
Name: stestdata
Version: 0.1.0
Summary: Variety of remote sensing data for testing
Home-page: https://github.com/sat-utils/sat-testdata
Author: Alireza J (scisco), Matthew Hanson (matthewhanson)
Author-email: alireza@developmentseed.org
License: MIT
Platform: UNKNOWN
Classifier: Framework :: Pytest
Classifier: Topic :: Scientific/Engineering :: GIS
Classifier: Topic :: Scientific/Engineering
Classifier: Intended Audience :: Developers
Classifier: Intended Audience :: Science/Research
Classifier: License :: Freeware
Classifier: Programming Language :: Python :: 2.7
Classifier: Programming Language :: Python :: 3.3
Classifier: Programming Language :: Python :: 3.4
Classifier: Programming Language :: Python :: 3.5
